gdrepl/__init__.py
gdrepl/__main__.py
gdrepl/_version.py
gdrepl/client.py
gdrepl/commands.py
gdrepl/config.py
gdrepl/constants.py
gdrepl/find_godot.py
gdrepl/gdserver.gd
gdrepl/gdserverv4.gd
gdrepl/history.py
gdrepl/keybindings.py
gdrepl/main.py
gdrepl/styles.py
gdrepl/ui.py
gdrepl/websocketserver.gd
gdrepl-0.1.0.dist-info/METADATA
gdrepl-0.1.0.dist-info/WHEEL
gdrepl-0.1.0.dist-info/entry_points.txt
gdrepl-0.1.0.dist-info/licenses/LICENSE.md
gdrepl-0.1.0.dist-info/RECORD
