Metadata-Version: 2.4
Name: gdrepl
Version: 0.1.0
Summary: Proof of concept REPL for Godot's GDScript
Project-URL: Homepage, https://github.com/matheusfillipe/GDScript-REPL
Project-URL: Repository, https://github.com/matheusfillipe/GDScript-REPL
Project-URL: Issues, https://github.com/matheusfillipe/GDScript-REPL/issues
Author-email: Matheus Fillipe <mattf@tilde.club>
License-Expression: MIT
License-File: LICENSE.md
Keywords: gamedev,gdscript,godot,interpreter,repl
Classifier: Development Status :: 5 - Production/Stable
Classifier: Environment :: Console
Classifier: Intended Audience :: Developers
Classifier: License :: OSI Approved :: MIT License
Classifier: Operating System :: OS Independent
Classifier: Programming Language :: Python :: 3
Classifier: Programming Language :: Python :: 3.9
Classifier: Programming Language :: Python :: 3.10
Classifier: Programming Language :: Python :: 3.11
Classifier: Programming Language :: Python :: 3.12
Classifier: Programming Language :: Python :: 3.13
Classifier: Topic :: Software Development :: Interpreters
Requires-Python: >=3.9
Requires-Dist: click-default-group>=1.2
Requires-Dist: click>=8.1
Requires-Dist: pexpect>=4.9
Requires-Dist: prompt-toolkit>=3.0
Requires-Dist: pygments>=2.17
Requires-Dist: pyyaml>=6.0
Requires-Dist: websocket-client>=1.7
